MySQLdb/__init__.py
MySQLdb/_exceptions.py
MySQLdb/_mysql.cp38-win_amd64.pyd
MySQLdb/connections.py
MySQLdb/converters.py
MySQLdb/cursors.py
MySQLdb/release.py
MySQLdb/times.py
MySQLdb/constants/CLIENT.py
MySQLdb/constants/CR.py
MySQLdb/constants/ER.py
MySQLdb/constants/FIELD_TYPE.py
MySQLdb/constants/FLAG.py
MySQLdb/constants/__init__.py
mysqlclient_collate-2.1.1.post2.dist-info/LICENSE
mysqlclient_collate-2.1.1.post2.dist-info/METADATA
mysqlclient_collate-2.1.1.post2.dist-info/WHEEL
mysqlclient_collate-2.1.1.post2.dist-info/top_level.txt
mysqlclient_collate-2.1.1.post2.dist-info/RECORD
