Metadata-Version: 2.1
Name: mysqlclient-collate
Version: 2.1.1.post2
Summary: Python interface to MySQL
Home-page: https://github.com/coderedcorp/mysqlclient-collate
Author: CodeRed LLC
Author-email: info@coderedcorp.com
License: GPL
Platform: ALL
Classifier: Development Status :: 5 - Production/Stable
Classifier: Environment :: Other Environment
Classifier: License :: OSI Approved :: GNU General Public License (GPL)
Classifier: Operating System :: MacOS :: MacOS X
Classifier: Operating System :: Microsoft :: Windows :: Windows NT/2000
Classifier: Operating System :: OS Independent
Classifier: Operating System :: POSIX
Classifier: Operating System :: POSIX :: Linux
Classifier: Operating System :: Unix
Classifier: Programming Language :: C
Classifier: Programming Language :: Python
Classifier: Programming Language :: Python :: 3
Classifier: Programming Language :: Python :: 3.6
Classifier: Programming Language :: Python :: 3.7
Classifier: Programming Language :: Python :: 3.8
Classifier: Programming Language :: Python :: 3.9
Classifier: Programming Language :: Python :: 3.10
Classifier: Topic :: Database
Classifier: Topic :: Database :: Database Engines/Servers
Requires-Python: >=3.5
